{"match_id":"2b9839de-a005-495e-adf0-019137a301dc","map":"AmbroseValley","date":"February_13","duration_ms":659000,"human_count":1,"bot_count":0,"players":[{"user_id":"6317200c-a1fc-41fd-9ca4-bf5bbcf27b40","player_type":"human","color":[255,200,50],"events":[{"t":0,"e":"P","px":692,"py":236},{"t":45000,"e":"P","px":671,"py":247},{"t":50000,"e":"P","px":642,"py":255},{"t":51000,"e":"L","px":641,"py":256},{"t":55000,"e":"P","px":626,"py":259},{"t":60000,"e":"P","px":596,"py":255},{"t":65000,"e":"P","px":569,"py":254},{"t":70000,"e":"P","px":555,"py":260},{"t":72000,"e":"L","px":555,"py":260},{"t":75000,"e":"P","px":539,"py":252},{"t":80000,"e":"P","px":517,"py":238},{"t":85000,"e":"P","px":509,"py":232},{"t":87000,"e":"L","px":509,"py":232},{"t":91000,"e":"P","px":499,"py":223},{"t":96000,"e":"P","px":498,"py":225},{"t":101000,"e":"P","px":501,"py":221},{"t":106000,"e":"P","px":482,"py":226},{"t":110000,"e":"L","px":471,"py":224},{"t":111000,"e":"P","px":471,"py":224},{"t":116000,"e":"P","px":470,"py":231},{"t":116000,"e":"L","px":470,"py":231},{"t":121000,"e":"P","px":467,"py":222},{"t":121000,"e":"BK","px":467,"py":222},{"t":126000,"e":"P","px":470,"py":215},{"t":130000,"e":"L","px":457,"py":210},{"t":131000,"e":"P","px":457,"py":210},{"t":133000,"e":"L","px":459,"py":213},{"t":133000,"e":"L","px":459,"py":213},{"t":136000,"e":"P","px":453,"py":215},{"t":139000,"e":"L","px":453,"py":216},{"t":141000,"e":"L","px":452,"py":219},{"t":141000,"e":"P","px":452,"py":219},{"t":144000,"e":"L","px":451,"py":221},{"t":151000,"e":"P","px":474,"py":208},{"t":156000,"e":"P","px":468,"py":222},{"t":161000,"e":"P","px":472,"py":211},{"t":164000,"e":"L","px":460,"py":212},{"t":166000,"e":"P","px":461,"py":215},{"t":171000,"e":"P","px":470,"py":231},{"t":171000,"e":"L","px":470,"py":231},{"t":176000,"e":"P","px":463,"py":229},{"t":176000,"e":"L","px":463,"py":229},{"t":177000,"e":"L","px":463,"py":229},{"t":193000,"e":"L","px":464,"py":230},{"t":196000,"e":"P","px":467,"py":231},{"t":201000,"e":"P","px":452,"py":233},{"t":206000,"e":"P","px":457,"py":236},{"t":211000,"e":"P","px":447,"py":266},{"t":216000,"e":"P","px":440,"py":286},{"t":221000,"e":"P","px":428,"py":294},{"t":226000,"e":"P","px":425,"py":279},{"t":231000,"e":"P","px":422,"py":247},{"t":236000,"e":"P","px":425,"py":230},{"t":241000,"e":"P","px":436,"py":217},{"t":246000,"e":"P","px":427,"py":202},{"t":247000,"e":"BK","px":427,"py":203},{"t":252000,"e":"L","px":428,"py":203},{"t":274000,"e":"L","px":428,"py":203},{"t":282000,"e":"P","px":425,"py":207},{"t":287000,"e":"P","px":428,"py":203},{"t":291000,"e":"L","px":428,"py":203},{"t":293000,"e":"L","px":428,"py":203},{"t":295000,"e":"L","px":428,"py":203},{"t":296000,"e":"L","px":428,"py":203},{"t":302000,"e":"P","px":419,"py":222},{"t":307000,"e":"P","px":398,"py":252},{"t":312000,"e":"P","px":394,"py":285},{"t":317000,"e":"P","px":389,"py":310},{"t":319000,"e":"L","px":389,"py":310},{"t":322000,"e":"P","px":386,"py":313},{"t":327000,"e":"P","px":383,"py":335},{"t":340000,"e":"L","px":383,"py":335},{"t":352000,"e":"P","px":370,"py":341},{"t":357000,"e":"P","px":385,"py":370},{"t":359000,"e":"L","px":391,"py":376},{"t":362000,"e":"P","px":391,"py":374},{"t":367000,"e":"P","px":388,"py":382},{"t":368000,"e":"L","px":388,"py":382},{"t":368000,"e":"L","px":388,"py":382},{"t":372000,"e":"P","px":390,"py":377},{"t":377000,"e":"P","px":391,"py":379},{"t":381000,"e":"L","px":400,"py":387},{"t":381000,"e":"L","px":400,"py":387},{"t":382000,"e":"P","px":400,"py":387},{"t":387000,"e":"P","px":396,"py":385},{"t":392000,"e":"P","px":389,"py":366},{"t":397000,"e":"P","px":379,"py":352},{"t":402000,"e":"P","px":372,"py":345},{"t":407000,"e":"P","px":361,"py":337},{"t":412000,"e":"P","px":347,"py":340},{"t":417000,"e":"P","px":332,"py":338},{"t":422000,"e":"P","px":310,"py":349},{"t":427000,"e":"P","px":289,"py":373},{"t":432000,"e":"P","px":283,"py":394},{"t":437000,"e":"P","px":258,"py":415},{"t":443000,"e":"P","px":232,"py":425},{"t":448000,"e":"P","px":211,"py":430},{"t":453000,"e":"P","px":185,"py":442},{"t":458000,"e":"P","px":158,"py":445},{"t":463000,"e":"P","px":134,"py":440},{"t":463000,"e":"L","px":134,"py":440},{"t":468000,"e":"P","px":129,"py":422},{"t":473000,"e":"P","px":98,"py":410},{"t":476000,"e":"L","px":90,"py":408},{"t":478000,"e":"P","px":96,"py":413},{"t":483000,"e":"P","px":102,"py":418},{"t":483000,"e":"L","px":102,"py":418},{"t":488000,"e":"P","px":89,"py":417},{"t":493000,"e":"P","px":88,"py":418},{"t":503000,"e":"P","px":94,"py":416},{"t":506000,"e":"L","px":106,"py":406},{"t":508000,"e":"P","px":105,"py":404},{"t":513000,"e":"P","px":100,"py":407},{"t":518000,"e":"P","px":94,"py":402},{"t":523000,"e":"P","px":95,"py":400},{"t":528000,"e":"P","px":109,"py":383},{"t":533000,"e":"P","px":134,"py":402},{"t":538000,"e":"P","px":160,"py":410},{"t":543000,"e":"P","px":179,"py":424},{"t":548000,"e":"P","px":189,"py":436},{"t":553000,"e":"P","px":199,"py":445},{"t":558000,"e":"P","px":223,"py":468},{"t":563000,"e":"P","px":245,"py":494},{"t":568000,"e":"L","px":261,"py":514},{"t":568000,"e":"P","px":262,"py":514},{"t":573000,"e":"P","px":256,"py":510},{"t":577000,"e":"BK","px":254,"py":515},{"t":578000,"e":"P","px":254,"py":515},{"t":583000,"e":"P","px":275,"py":524},{"t":584000,"e":"L","px":275,"py":524},{"t":584000,"e":"L","px":275,"py":524},{"t":588000,"e":"P","px":297,"py":533},{"t":593000,"e":"P","px":307,"py":537},{"t":598000,"e":"P","px":315,"py":534},{"t":603000,"e":"P","px":324,"py":531},{"t":608000,"e":"P","px":311,"py":538},{"t":613000,"e":"P","px":296,"py":537},{"t":618000,"e":"P","px":296,"py":538},{"t":622000,"e":"L","px":296,"py":538},{"t":624000,"e":"P","px":295,"py":533},{"t":629000,"e":"P","px":265,"py":525},{"t":634000,"e":"P","px":240,"py":507},{"t":639000,"e":"P","px":216,"py":490},{"t":644000,"e":"P","px":193,"py":475},{"t":649000,"e":"P","px":178,"py":449},{"t":654000,"e":"P","px":150,"py":441},{"t":659000,"e":"P","px":154,"py":425}]}]}