{"match_id":"b5ed9b5b-d24d-49b4-8eac-28573a655e44","map":"Lockdown","date":"February_10","duration_ms":365000,"human_count":1,"bot_count":0,"players":[{"user_id":"5a225352-5e13-4c77-b62f-7c1594762fb5","player_type":"human","color":[255,200,50],"events":[{"t":0,"e":"P","px":158,"py":373},{"t":25000,"e":"P","px":162,"py":380},{"t":30000,"e":"P","px":158,"py":388},{"t":35000,"e":"P","px":151,"py":393},{"t":40000,"e":"P","px":152,"py":383},{"t":45000,"e":"P","px":152,"py":359},{"t":55000,"e":"P","px":163,"py":373},{"t":60000,"e":"P","px":180,"py":379},{"t":65000,"e":"P","px":194,"py":382},{"t":70000,"e":"P","px":197,"py":384},{"t":75000,"e":"L","px":199,"py":383},{"t":75000,"e":"P","px":199,"py":383},{"t":80000,"e":"P","px":196,"py":390},{"t":83000,"e":"L","px":196,"py":390},{"t":90000,"e":"P","px":203,"py":388},{"t":96000,"e":"P","px":197,"py":378},{"t":101000,"e":"L","px":198,"py":374},{"t":111000,"e":"P","px":211,"py":384},{"t":116000,"e":"P","px":217,"py":393},{"t":120000,"e":"L","px":210,"py":399},{"t":121000,"e":"P","px":210,"py":399},{"t":126000,"e":"P","px":214,"py":397},{"t":131000,"e":"P","px":216,"py":398},{"t":135000,"e":"L","px":224,"py":397},{"t":136000,"e":"P","px":224,"py":397},{"t":141000,"e":"P","px":217,"py":399},{"t":146000,"e":"P","px":214,"py":391},{"t":151000,"e":"P","px":217,"py":380},{"t":156000,"e":"L","px":210,"py":375},{"t":156000,"e":"P","px":210,"py":375},{"t":161000,"e":"P","px":220,"py":376},{"t":166000,"e":"P","px":226,"py":379},{"t":171000,"e":"P","px":218,"py":381},{"t":176000,"e":"P","px":226,"py":389},{"t":181000,"e":"P","px":221,"py":383},{"t":186000,"e":"P","px":224,"py":387},{"t":191000,"e":"P","px":227,"py":389},{"t":201000,"e":"P","px":226,"py":399},{"t":206000,"e":"P","px":225,"py":407},{"t":211000,"e":"P","px":239,"py":404},{"t":216000,"e":"P","px":262,"py":414},{"t":221000,"e":"P","px":269,"py":414},{"t":226000,"e":"P","px":279,"py":403},{"t":231000,"e":"P","px":290,"py":416},{"t":236000,"e":"P","px":303,"py":428},{"t":241000,"e":"P","px":313,"py":444},{"t":246000,"e":"P","px":316,"py":454},{"t":251000,"e":"P","px":320,"py":465},{"t":256000,"e":"P","px":325,"py":471},{"t":261000,"e":"P","px":337,"py":480},{"t":266000,"e":"P","px":344,"py":493},{"t":271000,"e":"P","px":322,"py":508},{"t":277000,"e":"P","px":316,"py":541},{"t":282000,"e":"P","px":336,"py":559},{"t":287000,"e":"P","px":336,"py":569},{"t":292000,"e":"P","px":329,"py":574},{"t":297000,"e":"P","px":327,"py":580},{"t":301000,"e":"L","px":330,"py":582},{"t":302000,"e":"P","px":330,"py":582},{"t":307000,"e":"P","px":325,"py":583},{"t":312000,"e":"P","px":329,"py":570},{"t":314000,"e":"BK","px":329,"py":570},{"t":326000,"e":"L","px":330,"py":570},{"t":347000,"e":"P","px":324,"py":569},{"t":352000,"e":"P","px":341,"py":568},{"t":357000,"e":"P","px":341,"py":570},{"t":362000,"e":"BD","px":335,"py":561},{"t":362000,"e":"P","px":335,"py":561},{"t":365000,"e":"BK","px":335,"py":561}]}]}